[
    {
        "uid": "b2d76538-41c8-4c04-a8b3-2cee03a01adc",
        "kind": "Creek",
        "x": 906.9001944728808,
        "y": 1124.9953266635382
    },
    {
        "uid": "d4738d73-a576-4f33-a13b-c662353a219a",
        "kind": "Creek",
        "x": 553.1508347290716,
        "y": 816.4077684621105
    },
    {
        "uid": "936f8f8b-4fbb-4afa-8096-946272af68c8",
        "kind": "Creek",
        "x": 851.6561156467033,
        "y": 313.4953335592853
    },
    {
        "uid": "2e96479f-8dda-4315-8892-3ef3d7be115e",
        "kind": "Creek",
        "x": 725.7259213615976,
        "y": 1329.8111539792703
    },
    {
        "uid": "2e2bd690-3540-4ac8-b3c8-7b6a81f0f297",
        "kind": "Creek",
        "x": 553.5965562432807,
        "y": 732.2381657892128
    },
    {
        "uid": "0dd9c2eb-e114-48d6-a857-1a07ba38b964",
        "kind": "Creek",
        "x": 504.07293727619333,
        "y": 1088.2681506073056
    },
    {
        "uid": "ccfe2259-883b-4f46-9747-95cff0226993",
        "kind": "EmergencySite",
        "x": 1092.6842850492694,
        "y": 434.529251387242
    },
    {
        "uid": "eb7a0f24-3534-4988-9a5d-7dd84f891c29",
        "kind": "Creek",
        "x": 844.2783006558153,
        "y": 1203.1805637319912
    },
    {
        "uid": "17d172cc-cb0d-4f22-a04e-a76d51b1b3e2",
        "kind": "Creek",
        "x": 1015.1779553502986,
        "y": 890.4612485669979
    },
    {
        "uid": "99d46df9-df35-4522-85dd-752fd45376fd",
        "kind": "Creek",
        "x": 922.0105184324042,
        "y": 277.7085813120632
    },
    {
        "uid": "155d692b-056e-43c2-b6a3-7a3058a4bd5a",
        "kind": "Creek",
        "x": 560.247106714227,
        "y": 765.8454474411957
    }
]